{"name": "Kiddy Sun in Fantasia", "overview": "Kiddy Sun in Fantasia is a game developed by Hudson Soft and released by Eratech in 1987. It seems just a hacked game but in fact it was licensed for the Taiwanese division of Hudson Soft.<br><br>The game is basically a hack of Adventure Island. The game starts on Area 1, Round 2, as opposed to the first stage in the game. In addition, many sprites have been changed. Master Higgins is missing in action, and instead of collecting fruit, the player collects other delicacies. The enemies and bosses have also been reworked, and the level order has been tweaked. Last but not least, new music has been added to the game.", "platform": "Nintendo Entertainment System", "release_date": "1987", "game_type": "Released", "esrb": "Not Rated", "developers": "Hudson Soft", "publishers": "Eratech", "genres": "Action", "max_players": "1", "cooperative": "No", "rating": "4.33", "wikipedia": "", "video_link": "", "launchbox_gamesdb_link": "https://gamesdb.launchbox-app.com/games/details/93702"}