{"name": "Inside Outing", "overview": "Inside Outing is an isometric arcade adventure game released by The Edge in 1988 for the ZX Spectrum, Amstrad CPC and Commodore 64. It was later also released for the Atari ST and Amiga with the title Raffles. Subsequent 8-bit reissues were also given this title. It was released in the U.S. by Epyx as Devon Aire in the Hidden Diamond Caper.<br><br>An eccentric millionaire has died without leaving a will, instead hiding his money and gems in obscure places around his large house. His widow has hired a professional thief to find and retrieve these items. However, the dead millionaire's strange pets have now overrun the mansion and do not take kindly to interlopers.", "platform": "Amstrad CPC", "release_date": "1988", "game_type": "Released", "esrb": "Not Rated", "developers": "The Edge", "publishers": "The Edge", "genres": "Adventure", "max_players": "1", "cooperative": "No", "rating": "None", "wikipedia": "", "video_link": "https://www.youtube.com/watch?v=l2UeoS5F3r0", "launchbox_gamesdb_link": "https://gamesdb.launchbox-app.com/games/details/109071"}