{"altername_name": [], "name": "Jot-a-Word Genie", "overview": "A puzzle word game from Tim Delaney and released by BCI Software in 1983. Guess the words and outscore the computer. A computerized version o! the old five letter word game. Simply pick a secret five letter word (one of the almost 5000 words contained on the disk) and then play against the Jot-A-Word Genie or simply play a solitaire version. Start by typing in a five letter word. The Genie responds by telling you how many letters your guess and the secret work have in common. Don't try to cheat, because the Genie is too smart and it will not accept non- words or continue a game that you have given it wrong scores. This is a simple but stimulating game for ages 9 to senior citizen, A real challenge to your intellect, reasoning powers, logic and deduction skills. It's simply hard to beat; as a fun and educational experience? Graphics and music add to the enjoyment.", "platform": "Commodore 64", "release_date": "1983", "game_type": "Released", "esrb": "Not Rated", "developers": "Tim Delaney", "publishers": "BCI Software", "genres": "Puzzle", "max_players": "1", "cooperative": "No", "rating": "5", "wikipedia": "", "video_link": "", "launchbox_gamesdb_link": "https://gamesdb.launchbox-app.com/games/details/75926-jot-a-word-genie\n"}