{"altername_name": [], "name": "Keloglan", "overview": "Keloglan (stylized as Kelo\u011flan on the title screen) is a Turkish language graphic text adventure for the Commodore 64 published in 1989 by Byte Computer. Keloglan is based on a fictional Turkish character of the same name from the nation's folklore/mythology. Help Keloglan to awaken the beautiful princess from death sleep. Be sneaky! Kelo\u011flan,may be the the first Turkish commercial game released (we haven't come across an older commercially available game yet), is an adventure game made with the game editor named GAC (graphic adventure creator). Each screen of the game is graphically represented and the last screen is also available.", "platform": "Commodore 64", "release_date": "1989", "game_type": "Released", "esrb": "Not Rated", "developers": "", "publishers": "Byte Computer", "genres": "Adventure", "max_players": "1", "cooperative": "No", "rating": "None", "wikipedia": "", "video_link": "", "launchbox_gamesdb_link": "https://gamesdb.launchbox-app.com/games/details/122228-keloglan\n"}