{"altername_name": [], "name": "Lords", "overview": "Lords is a Strategy game, published by Kingsoft, which was released in 1991. Lords is a 1-player strategy game for the Commodore 64. The player controls a god-like figure that looks down upon their populace, and helps guide them to victory against another group. The game can be played on forest or desert terrain on a large scrolling map, with the the competing groups starting on opposites ends of the map. The player can give instructions to their populace, who builds houses and castles. The player can also cast magic disasters upon the enemy nation, including: lightning bolts, poison, decay, and changes in terrain. The power to use these powers builds over time, and the player will become temporarily powerless after using larger disasters.", "platform": "Commodore 64", "release_date": "1991", "game_type": "Released", "esrb": "Not Rated", "developers": "", "publishers": "Kingsoft", "genres": "Strategy", "max_players": "1", "cooperative": "No", "rating": "None", "wikipedia": "", "video_link": "", "launchbox_gamesdb_link": "https://gamesdb.launchbox-app.com/games/details/84847-lords\n"}