{"altername_name": [], "name": "Plundered Hearts", "overview": "Plundered Hearts is an interactive fiction computer game created by Amy Briggs and published by Infocom in 1987. It was released simultaneously for several popular computer platforms of the time, such as the PC and Commodore 64. Plundered Hearts was Infocom's first (and only) game in the \"romance\" genre. It is Infocom's twenty-eighth game. Plundered Hearts is a text adventure game set in the late 1600's. The player takes control of a young Englishwoman who finds out that her father is sick. In order to take care of him, she travels to the West Indies. But on the way her ship is attacked by pirates, and she is carried away by their captain. Though still determined to find and help her father, the young woman discovers that perhaps she may find romance where she least expected it.", "platform": "Commodore 64", "release_date": "1987", "game_type": "Released", "esrb": "Not Rated", "developers": "Amy Briggs", "publishers": "Infocom, Inc.", "genres": "Adventure", "max_players": "1", "cooperative": "No", "rating": "3", "wikipedia": "https://en.wikipedia.org/wiki/Plundered_Hearts", "video_link": "", "launchbox_gamesdb_link": "https://gamesdb.launchbox-app.com/games/details/30416-plundered-hearts\n"}