{"altername_name": ["Get Dexter"], "name": "Crafton & Xunk", "overview": "Crafton & Xunk is a Graphic adventure game, originally released for the Amstrad CPC in 1986. It was programmed by Remi Herbulot, with graphics by Michel Rho, and was published in France by ERE Informatique and by PSS in Britain. An Atari ST version was released in 1987. The game is played out in isometric area with a futuristic sci-fi plot with puzzle solving. Reaction from the games industry and magazines was generally positive, gaining accolades and high ratings in reviews. A sequel, Get Dexter 2, was released in 1988. Plot: In 2912 a war rages on earth and is escalating out of control. If the Central Galactic Control Computer on Earth is destroyed then all life on the planets will perish with it. The council of Sages give Dexter, an android expert in dangerous missions, and Scooter his trusty Podocephalus, the mission to infiltrate the computer centre and copy the memory in order that Galactic life can continue.", "platform": "Microsoft MSX2", "release_date": "1988", "game_type": "Released", "esrb": "Not Rated", "developers": "Michel Rho", "publishers": "Ere Informatique", "genres": "Adventure", "max_players": "1", "cooperative": "No", "rating": "None", "wikipedia": "", "video_link": "", "launchbox_gamesdb_link": "https://gamesdb.launchbox-app.com/games/details/117659-crafton-xunk\n"}