{"altername_name": [], "name": "Another Mind", "overview": "Another Mind is an adventure game created by Squaresoft (now Square Enix) for Sony PlayStation and released in November 12, 1998 in Japan. The game is extremely obscure, having been released in the wake of Square's other titles Xenogears and Parasite Eve, and it remains unreleased in the rest of the world. A 16 year-old girl named Hitomi Hayama is involved in a car accident and admitted to a hospital. Upon waking, she realizes that another being, albeit a mind, has taken residence in her head. The player takes on the role on this separate consciousness. The game features an interactive system reminiscent of text-based adventure games that is called simply Dialog System with which the player can communicate with Hitomi. It consists of context-sensitive parts of phrases selectable via menus that can be put together to create a complete phrases. The player can change the course of the story or their relationship with Hitomi depending on the answers given, and multiple endings are possible. Instead of using CGI or anime, real actors are used in the game's cutscenes and full motion videos. Characters' emotions are conveyed through animated emoticons.", "platform": "Sony Playstation", "release_date": "November 12, 1998", "game_type": "Released", "esrb": "", "developers": "Square", "publishers": "Square", "genres": "Adventure", "max_players": "1", "cooperative": "No", "rating": "3.71", "wikipedia": "https://en.wikipedia.org/wiki/Another_Mind_(video_game)", "video_link": "https://www.youtube.com/watch?v=swGR3vbQAJg", "launchbox_gamesdb_link": "https://gamesdb.launchbox-app.com/games/details/105491-another-mind\n"}