{"name": "The Crystal Rainforest", "overview": "The Crystal Rain Forest is an educational puzzle game developed and published by Sherston Software for use in primary schools. It was originally released in 1992 for the Acorn Archimedes.<br>The game takes place on the planet Oglo. In the kingdom of Azon, the last remaining rainforest is being cut down by the antagonistic \"Cut and Run Gang\". The king of Azon ordered the Cut and Run Gang to stop threatening the rainforest, and is shortly shot by a poison dart. The two protagonists must take part in a variety of settings and activities to retrieve the magical rainforest crystals to save the king and stop the deforestation of the planet.<br>The game is presented in a first-person perspective, in which the player has to use various controls and mechanisms to explore the dense rainforests and solve puzzles. The game contains nine fully narrated interactive activities which includes machinery, puzzles, computer programmes and control mechanisms. The player-characters takes part in various scenarios including puzzle solving and programming.", "platform": "Acorn Archimedes", "release_date": "1992", "game_type": "Released", "esrb": "", "developers": "Sherston", "publishers": "Sherston", "genres": "Education", "max_players": "1", "cooperative": "No", "rating": "4.17", "wikipedia": "", "video_link": "", "launchbox_gamesdb_link": "https://gamesdb.launchbox-app.com/games/details/80444"}