{"altername_name": [], "name": "Muppetville", "overview": "Muppetville is an educational software program for the Apple IIe computer released in 1986 by Sunburst Communications. It was intended for preschoolers, and was compatible with the Muppet Learning Keys keyboard. It was designed by Christopher Cerf, Mike Fish, Joni Jablonsky, and Anders McCarthy. The game featured Kermit the Frog, Miss Piggy, Fozzie Bear, Statler and Waldorf, Animal, Gonzo, Camilla the Chicken, Beaker, Dr. Bunsen Honeydew, and Sam the Eagle. It contains six basic education games: - Apartments: matching game for sounds - Factory: basic addition questions up to 10. - Hotel: matching card game for shapes - Movie House: learn a word that begins with each letter of the alphabet - School: matching game involving numbers - Zoo: choosing which of shapes is different from the others", "platform": "Apple II", "release_date": "1986", "game_type": "Released", "esrb": "Not Rated", "developers": "", "publishers": "Sunburst Communications", "genres": "Education", "max_players": "1", "cooperative": "No", "rating": "4.75", "wikipedia": "", "video_link": "https://www.youtube.com/watch?v=6Vfi8aF4Dio", "launchbox_gamesdb_link": "https://gamesdb.launchbox-app.com/games/details/114861-muppetville\n"}