{"altername_name": [], "name": "3D Ecco the Dolphin", "overview": "Ecco the Dolphin is an action-adventure game originally developed by Ed Annunziata and Novotrade International for the Sega Genesis and published by Sega in 1992. It is the first installment in the Ecco the Dolphin video game franchise. The player character is a bottlenose dolphin who travels through time to combat hostile extraterrestrials in Earth's oceans and on an alien spacecraft. 3D Ecco the Dolphin is a port of the game for the Nintendo 3DS as part of Sega's 3D Classics line. Along with stereoscopic 3D graphics and the option to choose between Japanese and international versions of the game, the port also adds 'Super Dolphin Mode', which decreases the difficulty by giving players invincibility and unlimited oxygen. The game was released on the Nintendo eShop in Japan on June 26, 2013, and in North America and Europe on December 12, 2013.", "platform": "Nintendo 3DS", "release_date": "June 26, 2013", "game_type": "Released", "esrb": "E - Everyone", "developers": "Sega", "publishers": "Sega", "genres": "Action", "max_players": "1", "cooperative": "No", "rating": "3.77", "wikipedia": "https://en.wikipedia.org/wiki/Ecco_the_Dolphin_(video_game)#Release", "video_link": "", "launchbox_gamesdb_link": "https://gamesdb.launchbox-app.com/games/details/96892-3d-ecco-the-dolphin\n"}