{"altername_name": [], "name": "BlazBlue: Clone Phantasma", "overview": "BlazBlue: Clone Phantasma is a 2012 3D arena fighting video game developed by Arc System Works, released as an eShop application for the Nintendo 3DS. It is the sequel to BlayzBloo: Super Melee Brawlers Battle Royale. The game was released in Japan on December 26, 2012 and North America on August 21, 2014. Characters: Ragna the Bloodedge Jin Kisaragi Noel Vermillion Rachel Alucard Taokaka Bang Shishigami Hazama Makoto Nanaya Platinum the Trinity Izayoi Reception: The game received \u201cgenerally unfavorable reviews\u201d according to the review aggregator Metacritic.Hardcore Gamer gave the game a 2/5, saying \"Unless you love BlazBlue and short-burst, super basic brawlers enough to drop $5.99, this will be far too superficial an endeavor to warrant a purchase.\"", "platform": "Nintendo 3DS", "release_date": "December 26, 2012", "game_type": "Released", "esrb": "", "developers": "Arc System Works", "publishers": "Arc System Works", "genres": "Fighting", "max_players": "", "cooperative": "No", "rating": "2.9", "wikipedia": "https://en.wikipedia.org/wiki/BlazBlue:_Clone_Phantasma", "video_link": "", "launchbox_gamesdb_link": "https://gamesdb.launchbox-app.com/games/details/96909-blazblue-clone-phantasma\n"}