{"altername_name": ["Pepe The Screwdriver"], "name": "Pepe \u015arubokr\u0119cik", "overview": "1995, the year Pepe \u015arubokr\u0119cik was released on Amiga. Made by Wildcard and published by Alderan. Pepe \u015arubokr\u0119cik is a platform arcade game where the player must collect designated number of screws on each level to gain access exit doors. The game is divided into stages, each stage consists of two levels divided into two boards full of hostile mechanised units. After collecting a single screw on the first board a new screw appears on the other one. The process repeats until the player collect the required quantity of screws. Every visit on the board enemies resurrects previously disposed enemies. Some enemies may be killed by jumping on their heads, the other may be only over jumped. The final part of the stage is played on a single screen, where Pepe the Screwdriver must defeat the final boss and his assistants. In addiction the stages are separated with mini games, such as puzzles on time.", "platform": "Commodore Amiga", "release_date": "1995", "game_type": "Released", "esrb": "Not Rated", "developers": "Wildcard", "publishers": "Alderan", "genres": "Platform", "max_players": "1", "cooperative": "No", "rating": "5", "wikipedia": "", "video_link": "", "launchbox_gamesdb_link": "https://gamesdb.launchbox-app.com/games/details/161781-pepe-srubokrecik\n"}