{"name": "Phase Zero", "overview": "Phase Zero is an unreleased action-shooter video game that was in development by Hyper Image Productions and originally planned to be published by Atari Corporation on a scheduled September 1995 release date exclusively for the Atari Jaguar. It was the only game in development by Hyper Image.<br><br>Assuming the role of a newcomer pilot from the titular squadron assigned to fight against an rival organization only known as The Collective in a foreign planet, players take control of a windowless VTV hovertank craft called Hunter in order to complete a series of missions and tasks, while battling against enemy VTV hovertanks. Hyper Image was originally working on a top-down shooter for the Super Nintendo Entertainment System, before the team later moved to the Jaguar with Phase Zero and opted to use their own interpretation of the heightmap technique to render the landscapes and visuals, in addition of also placing emphasis on LAN play for multiplayer.", "platform": "Atari Jaguar", "release_date": "1995", "game_type": "Unreleased", "esrb": "Not Rated", "developers": "Hyper Image", "publishers": "Atari Corporation", "genres": "Shooter", "max_players": "1", "cooperative": "No", "rating": "1.5", "wikipedia": "", "video_link": "", "launchbox_gamesdb_link": "https://gamesdb.launchbox-app.com/games/details/106806"}