{"name": "Dragon Ball Z: V.R.V.S.", "overview": "Dragon Ball Z: V.R.V.S. is a fighting game released in 1994 for the Sega System 32 arcade platform by Sega and Banpresto. Although the game is in 2D, it uses camera angles positioned behind the characters to create a 3D-like experience. The game is controlled with a joysick and 3 buttons; a deluxe edition of the game features motion sensors that allow the player to move his or her body to control the character in the game. The object of the game is to defeat six opponents. The playable characters are Goku, Gohan, Piccolo, Vegeta, and Future Trunks. The final boss is an original character named Ozotto.", "platform": "Arcade", "release_date": "1994", "game_type": "Released", "esrb": "Not Rated", "developers": "Banpresto", "publishers": "Sega", "genres": "Fighting", "max_players": "2", "cooperative": "No", "rating": "3.48", "wikipedia": "", "video_link": "https://www.youtube.com/watch?v=hM6vdRFPj_U", "launchbox_gamesdb_link": "https://gamesdb.launchbox-app.com/games/details/35992"}