{"name": "Fester's Quest", "overview": "Uncle Fester's Quest: The Addams Family (PlayChoice-10) is a Maze / Shooter Large game developed by Sunsoft (Nintendo of America license) in 1989 for the Arcade.<br><br>It's just a kidnapping. Of an entire day. By an alien UFO! Will Fester sit still for this? The quest begins. For starters, take on slime replicators, skeeters, globules and giant scorpions. Your health is at stake, not to mention your life! Will you whip the Alien Bosses or will they whip you? Lucky for you, this is a family affair. And what a family! Find your way to Thing and help is right at hand. In trouble? Just ring for Lurch. He'll give those aliens trouble with a capital \"L\". The fate of the whole city is in your hands, and we've saved the worst for last!", "platform": "Arcade", "release_date": "1989", "game_type": "Released", "esrb": "Not Rated", "developers": "Sunsoft", "publishers": "Nintendo of America", "genres": "Shooter", "max_players": "2", "cooperative": "No", "rating": "3.25", "wikipedia": "", "video_link": "", "launchbox_gamesdb_link": "https://gamesdb.launchbox-app.com/games/details/116625"}