{"name": "Quiz & Dragons: Capcom Quiz Game", "overview": "Quiz & Dragons: Capcom Quiz Game is a question and answer game released in arcades in 1992. The game combined elements of RPGs with that of board games to create a unique twist to the quiz game genre. This game is included on Vol. 2 of Capcom Classics Collection for the PlayStation 2 and Xbox.<br><br>The game plays similar to a board game, where the player is given a predetermined dice roll that moves the player up to six spaces on the board; however, if the player is so given the choice, he can move to a space of his choosing if there is a fork in the road. After landing on a space, the player is given a series of questions (the amount of questions needed to be answered increase as the game progresses) in order to proceed back to the board for another dice roll. The player is given a time limit to answer the question, with points given that vary based on how fast the player answered the question correctly. If the player is successful in answering a question, one of the orbs above the enemy's portrait will light up, indicating a correct answer. If the player answers a question incorrectly, he will lose a life point. if the player loses all life points, the player must continue within the time limit or else the game is over.", "platform": "Arcade", "release_date": "1992", "game_type": "Released", "esrb": "Not Rated", "developers": "Capcom", "publishers": "Capcom", "genres": "Quiz", "max_players": "2", "cooperative": "No", "rating": "3.73", "wikipedia": "", "video_link": "https://www.youtube.com/watch?v=eBHIiV2xmaw", "launchbox_gamesdb_link": "https://gamesdb.launchbox-app.com/games/details/7955"}