{"name": "Sonic & Sega All-Stars Racing Arcade", "overview": "Sonic & Sega All-Stars Racing is a racing game developed by Sumo Digital. It stars characters from a wide range of Sega games, similar to the previously released Sega Superstars Tennis, also by Sumo Digital. Unlike Sega Superstars Tennis, Sonic & Sega All-Stars Racing is more skewed towards the Sonic the Hedgehog franchise, with roughly half the tracks based on the series and appoximately one third of the characters.<br><br>Its development was announced May 28, 2009, with the game being released in early 2010. It has so far been released for five home systems, including the Xbox 360, PlayStation 3, Wii, Nintendo DS, and PC. An arcade version of the game, titled Sonic & Sega All-Stars Racing Arcade and which runs on Sega's RingWide arcade hardware, was released in 2011. An iOS version was shown at E3 2011; this version is the only version of the game released in Japan.", "platform": "Arcade", "release_date": "2011", "game_type": "", "esrb": "", "developers": "Sumo Digital", "publishers": "Sega", "genres": "Racing", "max_players": "", "cooperative": "No", "rating": "4.12", "wikipedia": "", "video_link": "", "launchbox_gamesdb_link": "https://gamesdb.launchbox-app.com/games/details/88315"}