{"name": "Sonic Dash Extreme", "overview": "Sonic Dash Extreme is an arcade version of Sonic Dash mobile phone game developed by Sega Amusements, and released by Sega. An arcade version became available in selected places in the United Kingdom on May 2015. The arcade version features daily and all-time leaderboards and different control methods for large-sized d-pad controllers.<br><br>Sonic Dash Extreme is very similar to the original mobile phone game, but with several altered features. When starting the game, one of playable characters is chosen randomly for the player. Also, instead of using touchpad controls, the arcade cabinet features a large D-pad. By pressing left or right on this D-pad, the player can move their playable character sideways to avoid obstacles on the route, while pressing up on the D-Pad makes the playable character perform Spin Jump and pressing down on D-Pad activates the Roll.<br><br>The arcade game awards prizes in form of redemption tickets, which the player gets after passing the checkpoints between small sections. After passing through the last checkpoint, the player gets a rank depending on the amount of tickets and Rings the player has collected. After that, the player faces Dr. Eggman in his Egg Mobile in a boss battle, like in the original Sonic Dash. However, the of way of defeating him is different from that on the original Sonic Dash mobile phone game; after being bounced into the air by Springs, the player has to lock-on to and press down on D-pad to dash into one of the Egg Mobile's missile launchers three times. If the player fails to do so, they will lose the game.", "platform": "Arcade", "release_date": "2015", "game_type": "Released", "esrb": "Not Rated", "developers": "Sega Amusements", "publishers": "Sega", "genres": "Action", "max_players": "1", "cooperative": "No", "rating": "2.21", "wikipedia": "", "video_link": "", "launchbox_gamesdb_link": "https://gamesdb.launchbox-app.com/games/details/36190"}