{"name": "Space Battleship Yamato", "overview": "Space Battleship Yamato (\u5b87\u5b99\u6226\u8266\u30e4\u30de\u30c8 Uch\u016b Senkan Yamato) was a 1985 Japanese exclusive Laserdisc video game designed by Taito.  The game is based on the anime Japanese science fiction television series of the same name. Although not released in North America, the game shows two title screens, one in Japanese and another in English. The English title screen uses the Star Blazers: Space Cruiser Yamato naming used for the anime series broadcast on North American and Australian television<br><br>The arcade game is unrelated to the Star Blazer Sega game released in 1983. The arcade game features footage from the movies and series as well as  original animation created solely for the purpose of this laser disc game. The game play is a hybrid of different laser disc genres. It is mainly a collection of firing stages similar to Astron Belt and Cobra Command. It also has action sequences similar to those found in games like Ninja Hayate or Dragon's Lair.", "platform": "Arcade", "release_date": "1985", "game_type": "Released", "esrb": "Not Rated", "developers": "Taito", "publishers": "Taito", "genres": "Action", "max_players": "1", "cooperative": "No", "rating": "5", "wikipedia": "", "video_link": "https://youtu.be/Mcbmk9_qVYA", "launchbox_gamesdb_link": "https://gamesdb.launchbox-app.com/games/details/141744"}