{"name": "Super Hang-On (Mega-Tech)", "overview": "The Mega-Tech System is an arcade cabinet released by Sega in 1989, and Western counterpart to the Mega 6. It was based on the Sega Mega Drive home console, and was designed similarly to Nintendo's PlayChoice-10: players chose games from a menu of eight titles, with credits buying more play time (usually 1 minute per credit) rather than extra lives or continues; reaching a game over screen does not end the play session, and players can start over or choose a different game as long as there was some play time remaining. The Mega-Tech was not released in North America, though did see use in Asia and the PAL regions.<br><br>Super Hang-On is a motorcycle racing arcade game released by Sega, and the sequel to the acclaimed Hang-On. It was built on the Sega Hang-On hardware that powered Space Harrier. Versions of the arcade game also ran on the Sega OutRun hardware and Mega-Tech System.", "platform": "Arcade", "release_date": "1989", "game_type": "Released", "esrb": "", "developers": "Sega", "publishers": "Sega", "genres": "Racing", "max_players": "1", "cooperative": "No", "rating": "5", "wikipedia": "", "video_link": "https://youtu.be/VAUaG0v-nSU", "launchbox_gamesdb_link": "https://gamesdb.launchbox-app.com/games/details/139903"}