{"name": "Time Gal", "overview": "Time Gal is an interactive movie video game developed and published by Taito, and originally released in Japan for the arcades in 1985. It is an action game which uses full motion video (FMV) to display the on-screen action. The player must correctly choose the on-screen character's actions to progress the story. The pre-recorded animation for the game was produced by Toei Animation.<br><br>The game begins in 3001 AD with the theft of a time travel device. The thief, Luda, steals the device to take over the world by changing history. Reika, the protagonist also known as Time Gal, uses her own time travel device to pursue him; she travels to different time periods, such as 70,000,000 BC, 44 BC, 1588 AD, and 2010 AD, in search of Luda. Each time period is a scenario that presents a series of threats that must be avoided or confronted. Successfully navigating the sequences allows the player to progress to another period.", "platform": "Arcade", "release_date": "1985", "game_type": "Released", "esrb": "Not Rated", "developers": "Taito", "publishers": "Taito", "genres": "Action", "max_players": "1", "cooperative": "No", "rating": "3.35", "wikipedia": "", "video_link": "https://youtu.be/bCnrXVRV3Ak", "launchbox_gamesdb_link": "https://gamesdb.launchbox-app.com/games/details/82867"}