{"name": "Under Night In-Birth Exe:Late", "overview": "Under Night In-Birth (\u30a2\u30f3\u30c0\u30fc\u30ca\u30a4\u30c8\u30a4\u30f3\u30f4\u30a1\u30fc\u30b9, And\u0101 naito inv\u0101su) is a visual novel and 2D fighting game co-developed by Ecole Software and French-Bread, known for the licensed fighting game, Type-Moon\u2019s Melty Blood series. Since its initial arcade release in Japan, Under Night In-Birth has received numerous version updates, adjusting various system features and character attributes as well as adding several new playable characters to the roster. <br><br>Sega released the arcade version in Japan on September 20, 2012. A major revision of the arcade version, entitled Under Night In-Birth Exe:Late (\u30a2\u30f3\u30c0\u30fc\u30ca\u30a4\u30c8\u30a4\u30f3\u30f4\u30a1\u30fc\u30b9\u30a8\u30af\u30bb\u30ec\u30a4\u30c8, And\u0101 naito inv\u0101su ekusereito), was released on September 9, 2013. It was announced that Arc System Works would release the game for PlayStation 3 on July 24, 2014 in Japan, A 2015 release for North America and Europe was later announced. The North American release date, which was set for March 31, 2015, was revealed on the GameStop website. However, Aksys Games revealed the true release date for Exe:Late, they said that the game will be releasing on February 24, 2015 for the PlayStation 3, as well as confirmed there wouldn't be an English dub in Western releases. Exe:Late was also released on Steam for Microsoft Windows systems on July 12, 2016.", "platform": "Arcade", "release_date": "September 9, 2013", "game_type": "Released", "esrb": "Not Rated", "developers": "Arc System Works", "publishers": "Sega", "genres": "Fighting", "max_players": "2", "cooperative": "No", "rating": "4.5", "wikipedia": "", "video_link": "", "launchbox_gamesdb_link": "https://gamesdb.launchbox-app.com/games/details/136004"}