{"name": "Winning Run", "overview": "Winning Run is a first-person arcade racing simulation game developed and released by Namco in late December 1988 in Japan, before releasing internationally the following year. The player pilots a Formula One racer, with the objective being to complete each race in first place, all while avoiding opponents and other obstacles, such as flood-hit tunnels, pits and steep chambers. It was the very first game to run on the Namco System 21 arcade hardware, capable of 3D shaded polygons.<br><br>Winning Run is a first-person Formula One simulation racing video game. The player controls a Formula One racer, with the objective being to make it to the end of each race while in first place.Two gameplay modes are present \u2013 Easy and Technical, both of which affect the speed of the player's car. The player will need to first complete a \"qualifying lap\" in order to begin the final race, which will have the player pitted against twelve opponent vehicles. Common obstacles include pits, flood-hit tunnels and steep cambers.", "platform": "Arcade", "release_date": "1988", "game_type": "Released", "esrb": "Not Rated", "developers": "Namco", "publishers": "Namco", "genres": "Racing", "max_players": "", "cooperative": "No", "rating": "4.21", "wikipedia": "", "video_link": "", "launchbox_gamesdb_link": "https://gamesdb.launchbox-app.com/games/details/40150"}