{"altername_name": [], "name": "Buddy Mission Bond", "overview": "Buddy Mission BOND is an adventure game released for the Nintendo Switch in 2021. It is developed by Koei Tecmo and published by Nintendo with character design by Yusuke Murata, manga author of Eyeshield 21 and One-Punch Man. The game is a visual novel with two phases in each of the game's missions. The first part requires the player to choose two of the Team Bond members (consisting of Luke, Aaron, Mokuma, and Chesley) to form a pair of buddies who look for clues and interview citizens. The second phase has the buddies infiltrate the villain's base, the route of which depends on the clues found in the first phase.", "platform": "Nintendo Switch", "release_date": "January 29, 2021", "game_type": "Released", "esrb": "", "developers": "Koei Tecmo", "publishers": "Nintendo", "genres": "Adventure", "max_players": "", "cooperative": "No", "rating": "3.25", "wikipedia": "", "video_link": "", "launchbox_gamesdb_link": "https://gamesdb.launchbox-app.com/games/details/156604-buddy-mission-bond\n"}